__init__.py
ai_storyteller-0.1.dist-info/licenses/LICENSE
storyteller/__init__.py
storyteller/settings.py
storyteller/__pycache__/__init__.cpython-312.pyc
storyteller/__pycache__/__init__.cpython-313.pyc
storyteller/__pycache__/settings.cpython-313.pyc
storyteller/modules/__init__.py
storyteller/modules/__pycache__/__init__.cpython-312.pyc
storyteller/modules/__pycache__/__init__.cpython-313.pyc
storyteller/modules/common/__init__.py
storyteller/modules/common/cache.py
storyteller/modules/common/config.py
storyteller/modules/common/data_export.py
storyteller/modules/common/helpers.py
storyteller/modules/common/media.py
storyteller/modules/common/progress_bar.py
storyteller/modules/common/storage.py
storyteller/modules/common/structured_outputs.py
storyteller/modules/common/__pycache__/__init__.cpython-312.pyc
storyteller/modules/common/__pycache__/__init__.cpython-313.pyc
storyteller/modules/common/__pycache__/data_export.cpython-312.pyc
storyteller/modules/common/__pycache__/data_export.cpython-313.pyc
storyteller/modules/common/__pycache__/media.cpython-313.pyc
storyteller/modules/common/__pycache__/progress_bar.cpython-312.pyc
storyteller/modules/common/__pycache__/progress_bar.cpython-313.pyc
storyteller/modules/common/__pycache__/storage.cpython-312.pyc
storyteller/modules/common/__pycache__/storage.cpython-313.pyc
storyteller/modules/common/__pycache__/structured_outputs.cpython-312.pyc
storyteller/modules/common/__pycache__/structured_outputs.cpython-313.pyc
storyteller/modules/st/__init__.py
storyteller/modules/st/chat.py
storyteller/modules/st/content.py
storyteller/modules/st/content_docx.py
storyteller/modules/st/enums.py
storyteller/modules/st/files.py
storyteller/modules/st/helpers.py
storyteller/modules/st/image_gen_calls.py
storyteller/modules/st/llm_calls.py
storyteller/modules/st/mcp_impl.py
storyteller/modules/st/option_choices.py
storyteller/modules/st/tool_impl.py
storyteller/modules/st/__pycache__/__init__.cpython-312.pyc
storyteller/modules/st/__pycache__/__init__.cpython-313.pyc
ai_storyteller-0.1.dist-info/METADATA
ai_storyteller-0.1.dist-info/WHEEL
ai_storyteller-0.1.dist-info/entry_points.txt
ai_storyteller-0.1.dist-info/top_level.txt
ai_storyteller-0.1.dist-info/RECORD
